Metadata-Version: 2.1
Name: probabulity-distributions
Version: 0.0.0
Summary: Gaussian and Binomial Distributions Distributions
Home-page: UNKNOWN
Author: Vinlaw ZP Mudehwe
Author-email: vmudehwe3661@gmail.com
License: UNKNOWN
Platform: UNKNOWN
